tensorcanvas/BaseShapes.py
tensorcanvas/__init__.py
tensor_canvas-0.1.8.dist-info/LICENSE
tensor_canvas-0.1.8.dist-info/METADATA
tensor_canvas-0.1.8.dist-info/WHEEL
tensor_canvas-0.1.8.dist-info/top_level.txt
tensor_canvas-0.1.8.dist-info/RECORD
