Metadata-Version: 2.1
Name: tensor-canvas
Version: 0.1.8
Summary: UNKNOWN
Home-page: https://github.com/pwhiddy/tensor-canvas
Author: Peter Whidden
Author-email: all.cows.like.to.moo@gmail.com
License: UNKNOWN
Platform: UNKNOWN
Classifier: Programming Language :: Python :: 3
Classifier: License :: OSI Approved :: MIT License
Classifier: Operating System :: OS Independent
Requires-Python: >=3.6
License-File: LICENSE
Requires-Dist: eagerpy
Requires-Dist: torch
